sam_djtools/__init__.py
sam_djtools/admin_models.py
sam_djtools/apps.py
sam_djtools/del_migrations.py
sam_djtools/navigate_records.py
sam_djtools/utils.py
sam_djtools/management/commands/resetdb.py
sam_djtools/static/sam_djtools/change_form_prev_next.js
sam_djtools/templates/admin/change_form.html
sam_djtools-1.2.42.dist-info/LICENSE.txt
sam_djtools-1.2.42.dist-info/METADATA
sam_djtools-1.2.42.dist-info/WHEEL
sam_djtools-1.2.42.dist-info/top_level.txt
sam_djtools-1.2.42.dist-info/RECORD
