Metadata-Version: 2.1
Name: sam-djtools
Version: 1.2.42
Summary: 1 sam_djtools.DbUtils, 2 sam_djtools.EmailUtils, 3. sam_djtools.GeneralUtils 4. Primary key based form navigation to explore next/prev records.
Home-page: https://github.com/humblesami/sam-djtools.git
Author-email: Sami Akram <samiakram@live.com>
Maintainer-email: Sami Akram <samiakram@live.com>
Project-URL: Changelog, https://github.com/humblesami/sam-djtools/CHANGES.rst
Project-URL: Code, https://github.com/humblesami/sam-djtools
Project-URL: Issue tracker, https://github.com/humblesami/sam-djtools/issues
Keywords: djtools,django-tools,form-navigation,email-in-thread
Classifier: Operating System :: OS Independent
Classifier: Programming Language :: Python :: 3
Requires-Python: >=3
License-File: LICENSE.txt
Requires-Dist: django>=3.2
Requires-Dist: django-currentuser>=0.6.0
